{
    "courseCode": "YSC1214",
    "courseCredit": "2",
    "description": "The main aim of the course is to introduce you to network thinking. How you could understand complex systems in the view of NETWORKS. In this course, we will: \u2022 explore the universe of technological, social, informational and biological networks around us \u2022 learn the basic concepts and tools for understanding the properties of networks \u2022 apply network science to gain insights in complex systems",
    "faculty": "Yale-NUS College",
    "title": "Networks"
}
