{
    "courseCode": "ME5701",
    "courseCredit": "4",
    "description": "This module teaches graduate students the various mathematical methods frequently used in the engineering research work. The topics include: Boundary value problems: classification of types and boundary conditions, hypergeometric equations, integral methods of solutions, numerical methods, finite difference and finite element methods, complex variables, conformal mapping, perturbation methods, statistics and probability. There is a compulsory Term Paper project for this module. This module is intended for graduate students and engineers interested in learning more of the various mathematical methods for solving advanced level engineering problems.",
    "faculty": "Engineering",
    "title": "Mathematics for Engineering Research"
}
