{
    "courseCode": "SE4226",
    "courseCredit": "5",
    "description": "This module provides students with both methodological and theoretical guidance for doing critical ethnography in Southeast Asia. Students will systematically learn about the fundamentals of practising ethnography in Southeast Asia and consider philosophical\u2010theoretical, disciplinary and ethical issues underpinning each stage of the ethnographic process.Different forms of ethnographic texts on Southeast Asia (including films) will be introduced and students will learn how to critically evaluate ethnographies. Students will have the opportunity to directly apply what they learn to their own research projects.",
    "faculty": "Arts and Social Science",
    "title": "Doing Ethnography in Southeast Asia"
}
