{
    "moduleCode": "BMA5515",
    "description": "To provide participants with basic understanding of the marketing research process and the scientific approach to information identification, collection and analysis for marketing decision-making. \n\nTo provide participants with the opportunity to design and execute a marketing research project.\n\nTo provide students with opportunities to examine, understand and interpret marketing research information.",
    "title": "Marketing Research",
    "faculty": "NUS Business School",
    "moduleCredit": "4"
}