{
    "moduleCode": "BMR5308",
    "description": "This course seeks to provide a basic framework of the\nPrivate Equity (PE) industry, expand on the principles of\nPE, with a particular focus on leveraged buyouts, and\nbring to life these principles through a \u201cpractitioners\nguide\u201d to the subject by the illustration of several live\ncase studies, guest CEO speakers, and panel\ndiscussions. At the end of this course, students will\nhave practical appreciation of how Private Equity\ncreates value, which techniques are equally applicable\nin any business situations, especially in the fast evolving\nbusiness environment.",
    "title": "Private Equity",
    "faculty": "NUS Business School",
    "moduleCredit": "2"
}