{
    "moduleCode": "BN5515",
    "description": "This course provides a comprehensive review of clinical\ndesign and evaluation for medical devices. It focuses on\nthe roles of clinical evaluations in product development\nincluding the roles of various pivotal trials and the\npostmarket study. The students will learn to design a\nclinical study taking into consideration the various aspects\nof the study like the ethics, treatment regimen, study\npopulation, the product effectiveness and safety endpoints.\nIn addition, the course will guide the students through a\nrigorous and systematic review of and integration of clinical\ndata follow by the drafting of a clinical evaluation report.",
    "title": "Clinical Design and Evaluation of Medical Devices",
    "faculty": "Engineering",
    "moduleCredit": "4"
}