{
    "moduleCode": "IE5504",
    "description": "Systems modelling and simulation are important tools in operations research. This subject covers the major aspects of modelling and techniques of computer simulation, model definition, construction of digital simulation models, design of simulation experiments, statistical verification of input data and results, simulation languages and advanced simulation concepts.",
    "title": "Systems Modelling and Advanced Simulation",
    "faculty": "Engineering",
    "moduleCredit": "4"
}