{
    "moduleCode": "IS5003",
    "description": "Digital platforms have disruptively transformed the way\nwe live, operate, and interact. Commercially, digital\nplatform companies have gained legendary success with\ntheir new business models in various industries. The\nmodule consists of four broad aspects, namely, (a) the\nfoundational theories in platform economics, (b) how to\nstrategize for and measure successful digital platform\nventure, (c) industry-level platforms and how businesses\ncan develop complementary technologies within a platform\necosystem, and (d) API management.",
    "title": "Platform Design and Economy",
    "faculty": "Computing",
    "moduleCredit": "4",
    "prereqTree": "IS2102"
}