{
    "moduleCode": "TEE3408",
    "description": "This module focuses on integration of analog circuits on silicon using CMOS technology. The topics covered include processing and modeling background, basic circuits, reference circuit design, single stage amplifiers, operational amplifiers, noise issues and advanced design methods",
    "title": "Integrated Analog Design",
    "faculty": "Cont and Lifelong Education",
    "moduleCredit": "4",
    "prereqTree": {
        "or": [
            "TEE2021",
            "TEE2027"
        ]
    }
}