{
    "moduleCode": "YHU3299",
    "description": "Exploring a transformative period in European history, this module will\nimmerse students in the vicissitudes of the turbulent Weimar Republic\n(1918-1933) through the lens of Berlin\u2019s roaring twenties and with\nparticular reference to the life and work of Magnus Hirschfeld, a Jewish\nphysician who was the face of scientifically enlightened sexual\nreformism, who travelled the globe as the \u2018Einstein of Sex\u2019 and who\nbecame a prime target of Nazi oppression as the Weimar Republic\ncollapsed in the early 1930s. Weimar Berlin offers an illuminating window\nonto Europe\u2019s ambivalences regarding democracy, liberalism, modernity,\nsocial and sexual change in the 20th century.",
    "title": "Weimar Berlin: Urbanity and Sexology Before the Nazis",
    "faculty": "Yale-NUS College",
    "moduleCredit": "5"
}