{
    "courseCode": "FMS1206M",
    "courseCredit": "4",
    "description": "This seminar seeks to help the freshmen to gain a fundamental understanding of Mathematics and a broader perspective of how it relates to other sciences. The major topics include the similarity and differences between Mathematics and the other sciences (Astronomy, Biology, Computer Science, etc.), the objectives and methodology in Science, and the role of Mathematics in Science.",
    "faculty": "Science",
    "preclusion": "Students who have read a Freshman Seminar before will be precluded from reading a second Freshman Seminar.\n\nStudents staying in Residential Colleges in UTown who will be reading or have read the Junior Seminars will be precluded from reading Freshman Seminar in the Faculty.",
    "title": "FS: Is Mathematics Science?"
}
