{
    "courseCode": "CM5241",
    "courseCredit": "4",
    "description": "Sample preparation, including miniaturised procedures of extraction; advanced coupled chromatography/mass spectrometry; advanced mass spectrometric techniques. Capillary electrophoresis: different modes of capillary electrophoresis, injection techniques, detection techniques and column technology. Scanning probe microscopy: scanning tunneling microscopy, atomic force microscopy, scanning electrochemical microscopy and scanning near-field optical microscopy. Determination of crystal and molecular structures by single crystal x-ray diffraction techniques.",
    "faculty": "Science",
    "prereqTree": "CM4242",
    "title": "Modern Analytical Techniques"
}
