{
    "courseCode": "ID3101",
    "courseCredit": "12",
    "description": "Objective - This module will emphasize the integrative nature of design. It will enable students to understand how technology should be applied to design and production. Topics - The module will focus on projects that require consideration for realism imposed by functional and technical constraints. The module will also emphasize the need for a rationalized design process that serves to comprehensively evaluate design ideas, concepts and intentions in the learning of design development. Targeted Students - Industrial design students.",
    "faculty": "Design and Environment",
    "preclusion": "Module not offered to non-industrial design students",
    "title": "Design 5"
}
