{
    "courseCode": "BMF5346",
    "courseCredit": "4",
    "description": "Venture capital and private equity are necessary to spur economic growth. This module covers private equity investment types including venture capital, growth capital, and buyouts. It also includes corporate venturing and cross-border structuring. Topics will cover the entire private equity investment cycle from fund raising and structuring; deal screening, due diligence, and valuation; investment negotiations; postinvestment value development; and eventual exits. Students will obtain a firm grasp of the workings behind PE and VC funds, as well as corporate ventures. It will also prepare budding entrepreneurs in their fundraising efforts as they negotiate from the other side of the table.",
    "faculty": "NUS Business School",
    "preclusion": "BMA5313\nBMA5313D\nBMS5113\nBMS5304",
    "title": "Venture Capital and Private Equity"
}
