{
    "attributes": {
        "su": true
    },
    "description": "This module is designed to concentrate on the study of two or more selected authors or texts in modern Chinese history, literature or philosophy. The course is suitable for students who are interested in modern Chinese history, literature or philosophy. Target students for this module are undergraduates across the University.",
    "faculty": "Arts and Social Science",
    "moduleCode": "CH2226",
    "moduleCredit": "4",
    "title": "Selected Authors/Texts I"
}