{
    "courseCode": "BMA5301",
    "courseCredit": "4",
    "description": "This course is an introduction to international finance and international financial management. Its purpose is to train students to relate financial analysis at the firm level with economic analysis at the macroeconomic level. In other words, the course tries to help financial analysts to relate their work to those of strategists and economists. Due to the objective of the course, the course has more weight on breadth than on depth regarding the coverage of the subjects.",
    "faculty": "NUS Business School",
    "title": "International Financial Management"
}
