{
    "courseCode": "MUT3211",
    "courseCredit": "3",
    "description": "This module is designed for students who wish to acquire written skills in tonal counterpoint and learn structural aspects of polyphonic music of the Baroque period. They will receive a full individual instruction on how to write a good counterpoint in all species step by step and then be initiated into various polyphonic genres, such as canon, invention, and fugue. Students will also participate in detailed analysis of fugues (and other contrapuntal music) by J. S. Bach and other composers and learn their structural principles.",
    "faculty": "YST Conservatory of Music",
    "title": "Tonal Counterpoint"
}
