{
    "courseCode": "LSM4255",
    "courseCredit": "4",
    "description": "The use of mathematics has a long history in life sciences and familiarity with basic, relevant mathematical techniques is becoming increasingly important for biologists. This course will focus on both current and classical themes in mathematical biology and will emphasise the acquisition of mathematical skills of relevance to current problems in ecology, evolution and epidemiology.",
    "faculty": "Science",
    "prereqTree": "LSM2253",
    "title": "Methods in Mathematical Biology"
}
