{
    "description": "This module will provide an overview of the contemporary U.S.-China relationship with particular focus on U.S. policymaking towards China. The module will review key issues that define the relationship, analyze U.S. security policy decision-making structures and consider how they shape the relationship. The course will conclude by discussing other Asian perspectives of the U.S.-China dyad and how third countries respond to shifts in the U.S.- China relationship.",
    "faculty": "LKY School of Public Policy",
    "moduleCode": "PP5512",
    "moduleCredit": "4",
    "title": "US-China Relations and Great Power Policy Making"
}