{
    "courseCode": "YHU3306",
    "courseCredit": "5",
    "description": "Imitation and Innovation in a time of Occupation. Between 1900 and 1946, under the occupation of the United States of America, the Philippines developed a body of literature that was subsequently called Philippine Literature in English. This module examines the pivotal historical conditions that allowed the formation and development of the first Filipino writers in English. Using the texts from this period as case studies, the module then investigates the role of imitation and innovation in artistic practices under colonial conditions and using these guiding principles lead the students to the creation and development of a manuscript of creative writing. This module fulfills the Creative Writing track in the Arts & Humanities major.",
    "faculty": "Yale-NUS College",
    "title": "Philippine Literature: American Period"
}
