{
    "courseCode": "LC5264",
    "courseCredit": "4",
    "description": "Regionalism is very much debated in contemporary trade policy discourse. Some regional trade agreements have involved deep integration, even going beyond the WTO. This course aims to ponder the relationship between the multilateral trading system and regional agreements. It will look at the manner in which regional agreements operate, and what effects they have on international trade.",
    "faculty": "Law",
    "preclusion": "LL4060B/LL5060B/LL6060B World Trade Law",
    "title": "WTO and Regional Integration"
}
