{
    "courseCode": "AH3550",
    "courseCredit": "4",
    "description": "Internships take place within the National Gallery of Singapore and relevant museums in Singapore and are vetted and approved by the Minor in Art History\u2019s convenor. All internships will focus on an aspect/aspects of art history to be decided by the student in consultation with his/her academic advisor and the museum of choice. The internship must involve the application of subject knowledge and theory in reflection to the work done.",
    "faculty": "Arts and Social Science",
    "prereqTree": "AH2101",
    "title": "Art History Internship"
}
