{
    "attributes": {
        "su": true
    },
    "courseCode": "GEH1031",
    "courseCredit": "4",
    "description": "The first part of the module covers the observations of celestial objects and their influences on the ancient cultures. Students will learn how calendars and astrology were developed, and how the fundamental laws of nature were discovered. The second part covers the use of telescopes and space missions to explore the universe. Discoveries of stars and galaxies and their impact on mankind's perceptions of the Universe will be explored. Students will learn how Earth formed as a planet that develops and sustains life. There will be a discussion on the latest developments in searching for Earth-like extraterrestrial objects, and explore their impacts on the societies.",
    "faculty": "Science",
    "preclusion": "GEK1520",
    "title": "Understanding the Universe"
}
