{
    "attributes": {
        "su": true
    },
    "description": "This module is designed for students wishing to understand the ethical and existential aspects of work. Key issues such as individual moral responsibility and attribution of corporate social responsibility will be examined from different perspectives. At the end of the module, students are expected to be able:",
    "faculty": "NUS Business School",
    "moduleCode": "GEK1020",
    "moduleCredit": "4",
    "preclusion": "GET1000",
    "title": "Ethics at Work: Rhyme, Reason and Reality"
}