{
    "courseCode": "SG5234",
    "courseCredit": "3",
    "description": "With the rapid growth of digital consumption and proliferation of various interfaces and technological devices, software development is constantly challenged to provide seamless experiences across various platforms and devices. Digital User Experience Design provides a variety of best practices under-pinned by design principles that help to address this issue. It is a holistic, multidisciplinary approach that leads to the development of useful and usable digital solutions. The course focuses on the discovery, analysis, design and evaluation of the needs of the various stakeholders and the role of user experience design throughout the software development lifecycle to deliver useful and usable systems.",
    "faculty": "Institute of Systems Science",
    "title": "Digital User Experience Design"
}
