{
    "courseCode": "SN4233",
    "courseCredit": "5",
    "description": "India is in the throes of substantial social, political and economic change. This module deals with social structures such as caste and class; political developments such as the political empowerment of backward caste groups and the relationship between the state and society captured in phenomena such as social movements; and economic change such as the movement from state control to regulation, from autarky to globalization, and the rise of sub national federal economies at the state level.",
    "faculty": "Arts and Social Science",
    "title": "Social, Political and Economic Change in India"
}
