{
    "attributes": {
        "su": true
    },
    "courseCode": "FMA1201D",
    "courseCredit": "4",
    "description": "The freshman seminar will introduce students to current economic thoughts and their application to economic development and policy in an open economy. The course will cover specific issues in trade policy, FDI activities, foreign labour and the role of international organizations such as the IMF and World Bank. It will also discuss the importance and differences in economic systems (institutions) on economic development, with particular emphasis on Asia and South\u2010East Asian countries.",
    "faculty": "Arts and Social Science",
    "title": "FS: Contemporary Issues in Trade Policy"
}
