{
    "attributes": {
        "su": true
    },
    "courseCode": "NM2212",
    "courseCredit": "4",
    "description": "This module provides an introduction to the principles and theories of visual design. Students will be exposed to the history and influences of visual design, and learn to appreciate the principles underlying visual design practice. Upon completing this module, students will be able to analyse, critique, and evaluate visual designs from both an aesthetic and a social and cultural perspective.",
    "faculty": "Arts and Social Science",
    "title": "Visual Design"
}
