{
    "attributes": {
        "su": true
    },
    "courseCode": "NUR1117",
    "courseCredit": "4",
    "description": "This module will develop knowledge and understanding of the normal structure and function of the human body. Following an introduction to the basic principles of anatomy and physiology, learning will take from the cell to organ-systems\u2019 approach to guide student learning. Body systems covered include: gastrointestinal, musculoskeletal, urinary and nervous systems. Knowledge of these systems is fundamental to, and underpins, the nursing practice modules for this semester.",
    "faculty": "Yong Loo Lin School (Medicine)",
    "preclusion": "AY1104 Anatomy\nPY1105 Physiology I\nPY1106 Physiology II",
    "title": "Anatomy and Physiology I"
}
