{
    "courseCode": "BDC6306",
    "courseCredit": "4",
    "description": "This module aims to provide the first-year PhD students with a rigorous introduction to the fundamentals of stochastic processes. Topics include (i) Continuous-time Markov chains, (ii) Renewal processes, (iii) Brownian motions, and (iv) Stochastic orders",
    "faculty": "NUS Business School",
    "fulfillRequirements": [
        "BDC6303",
        "IE6507"
    ],
    "preclusion": "IE6505 Stochastic Processes II",
    "prereqTree": {
        "or": [
            "BDC6112",
            "IE6004"
        ]
    },
    "title": "Stochastic Processes II"
}
