{
    "attributes": {
        "grsu": true
    },
    "courseCode": "IE5208",
    "courseCredit": "4",
    "description": "This module presents ideas of systems analysis and project management in a manner which demonstrates their essential unity. It uses the systems development cycle as a framework to discuss management of engineering and business projects from conception to termination. The module is divided into three interrelated parts: systems analysis and project management, project selection and organizational behavior, and systems and procedures in project planning and control.",
    "faculty": "Engineering",
    "title": "Systems Approach To Project Management"
}
